<?xml version="1.0" encoding="utf-8"?>
<wizard package="com.ctrip.zeus">
   <jdbc package="com.ctrip.zeus.dal" name="zeus">
      <datasource>
         <driver>com.mysql.jdbc.Driver</driver>
         <url>jdbc:mysql://localhost:3306/zeus</url>
         <user>root</user>
         <password>123456</password>
         <properties>useUnicode=true&amp;characterEncoding=UTF-8&amp;autoReconnect=true</properties>
      </datasource>
      <group name="core" package="com.ctrip.zeus.dal.core">
         <table name="group"/>
         <table name="group_health_check"/>
         <table name="group_server"/>
         <table name="group_load_balancing_method"/>
         <table name="group_slb"/>
         <table name="server"/>
         <table name="slb"/>
         <table name="slb_domain"/>
         <table name="slb_server"/>
         <table name="slb_vip"/>
         <table name="slb_virtual_server"/>
         <table name="status_group_server"/>
         <table name="status_server"/>
         <table name="archive_group"/>
         <table name="archive_slb"/>
         <table name="conf_group_active"/>
         <table name="conf_slb_active"/>
         <table name="build_info"/>
         <table name="nginx_conf"/>
         <table name="nginx_conf_server"/>
         <table name="nginx_conf_upstream"/>
         <table name="nginx_server"/>
         <table name="conf_group_slb_active"/>
         <table name="dist_lock"/>
         <table name="auth_resource"/>
         <table name="auth_role"/>
         <table name="auth_resource_role"/>
         <table name="auth_user_role"/>
         <table name="auth_user"/>
         <table name="auth_private_key"/>
         <table name="report"/>
         <table name="tag"/>
         <table name="tag_item"/>
         <table name="operation_log"/>
         <table name="property"/>
         <table name="property_item"/>
         <table name="property_key"/>
         <table name="r_vs_domain"/>
         <table name="snap_server_group"/>
         <table name="r_vs_slb"/>
         <table name="task"/>
         <table name="r_group_vs"/>
         <table name="r_group_gs"/>
         <table name="r_slb_slb_server"/>
         <table name="certificate"/>
         <table name="r_certificate_slb_server"/>
         <table name="r_group_vg"/>
         <table name="archive_vs"/>
         <table name="conf_slb_virtual_server_active"/>
         <table name="status_health_check"/>
         <table name="global_job"/>
         <table name="r_group_status"/>
         <table name="r_slb_status"/>
         <table name="r_vs_status"/>
         <table name="conf_slb_version"/>
         <table name="commit"/>
         <table name="nginx_conf_slb"/>
         <table name="group_history"/>
         <table name="group_server_status"/>
         <table name="app_info"/>
         <table name="report_queue"/>
         <table name="message_queue"/>
         <table name="default_page_active"/>
         <table name="default_page_file"/>
         <table name="default_page_server_active"/>
         <table name="status_check_count_slb"/>
         <table name="stats_group_slb"/>
         <table name="archive_commit"/>
         <table name="rule"/>
         <table name="traffic_policy"/>
         <table name="r_traffic_policy_vs"/>
         <table name="r_traffic_policy_group"/>
         <table name="archive_traffic_policy"/>
      </group>
   </jdbc>
</wizard>
